spicepy/__init__.py
spicepy/netlist.py
spicepy/netsolve.py
spicepy/transient_sources.py
spicepy-1.0.5.dist-info/LICENSE
spicepy-1.0.5.dist-info/METADATA
spicepy-1.0.5.dist-info/WHEEL
spicepy-1.0.5.dist-info/top_level.txt
spicepy-1.0.5.dist-info/RECORD
