Metadata-Version: 2.1
Name: spicepy
Version: 1.0.5
Summary: Circuit simulator written in Python
Home-page: https://github.com/giaccone/SpicePy
Author: Luca Giaccone
Author-email: luca.giaccone@polito.it
Project-URL: wiki, https://github.com/giaccone/SpicePy/wiki
Classifier: Programming Language :: Python :: 3
Classifier: License :: OSI Approved :: MIT License
Classifier: Operating System :: OS Independent
Requires-Python: >=3.6
License-File: LICENSE
